sc_crawler/__init__.py
sc_crawler/alembic.ini
sc_crawler/alembic_helpers.py
sc_crawler/cli.py
sc_crawler/insert.py
sc_crawler/inspector.py
sc_crawler/logger.py
sc_crawler/lookup.py
sc_crawler/str_utils.py
sc_crawler/table_bases.py
sc_crawler/table_fields.py
sc_crawler/tables.py
sc_crawler/tables_scd.py
sc_crawler/utils.py
sc_crawler/vendor_helpers.py
sc_crawler/alembic/env.py
sc_crawler/alembic/versions/19b010d3acdf_v1_1_4_memory_rename.py
sc_crawler/alembic/versions/4691089690c2_v0_1_1.py
sc_crawler/alembic/versions/5ae213bf06b3_v1_2_0_name_constraints.py
sc_crawler/alembic/versions/85c7256cc390_v1_1_4_add_cpu_ram_gpu_columns.py
sc_crawler/alembic/versions/865f5ee9f624_v1_2_0_rename_datacenter_to_region.py
sc_crawler/alembic/versions/98894dffd37c_v0_1_0.py
sc_crawler/alembic/versions/c8d2054e68eb_v1_1_4_benchmarks.py
sc_crawler/alembic/versions/dad8a1f0f455_v1_2_0_rename_datacenter_to_region-step2.py
sc_crawler/alembic/versions/f6bf6152039a_v0_1_3_step2.py
sc_crawler/alembic/versions/f6edf4a96a78_v0_1_3_step1.py
sc_crawler/vendors/__init__.py
sc_crawler/vendors/_helpers.py
sc_crawler/vendors/alicloud.py
sc_crawler/vendors/aliyun-old.py
sc_crawler/vendors/aws.py
sc_crawler/vendors/azure.py
sc_crawler/vendors/gcp.py
sc_crawler/vendors/hcloud.py
sc_crawler/vendors/ovh.py
sc_crawler/vendors/upcloud.py
sc_crawler/vendors/vendors.py
sparecores_crawler-0.3.3.dist-info/licenses/LICENSE
sparecores_crawler-0.3.3.dist-info/METADATA
sparecores_crawler-0.3.3.dist-info/WHEEL
sparecores_crawler-0.3.3.dist-info/entry_points.txt
sparecores_crawler-0.3.3.dist-info/top_level.txt
sparecores_crawler-0.3.3.dist-info/RECORD
