Metadata-Version: 2.4
Name: sparecores-crawler
Version: 0.3.3
Summary: Collect and standardize data on cloud server offerings, include specs, prices, and measured performance benchmarks.
Author: Gergely Daroczi, Attila Nagy
Maintainer-email: Spare Cores team <pkg@sparecores.com>
Project-URL: repository, https://github.com/SpareCores/sc-crawler
Project-URL: issues, https://github.com/SpareCores/sc-crawler/issues
Project-URL: documentation, https://sparecores.github.io/sc-crawler/
Project-URL: homepage, https://sparecores.com
Keywords: cloud,compute,etl,sqlite,spot-instances,cost-optimization
Classifier: Programming Language :: Python :: 3
Classifier: License :: OSI Approved :: Mozilla Public License 2.0 (MPL 2.0)
Classifier: Operating System :: OS Independent
Classifier: Development Status :: 5 - Production/Stable
Requires-Python: >=3.9
License-File: LICENSE
Requires-Dist: alembic
Requires-Dist: cachier>=3.1.1
Requires-Dist: pydantic==2.9.2
Requires-Dist: pydantic_extra_types
Requires-Dist: PyYAML
Requires-Dist: requests
Requires-Dist: rich
Requires-Dist: sqlmodel
Requires-Dist: typer
Provides-Extra: mkdocs
Requires-Dist: markdown; extra == "mkdocs"
Requires-Dist: mkdocs; extra == "mkdocs"
Requires-Dist: mkdocs-material[imaging]; extra == "mkdocs"
Requires-Dist: mkdocs-material-extensions; extra == "mkdocs"
Requires-Dist: mkdocs-autorefs; extra == "mkdocs"
Requires-Dist: mkdocs-gen-files; extra == "mkdocs"
Requires-Dist: mkdocs-literate-nav; extra == "mkdocs"
Requires-Dist: mkdocs-section-index; extra == "mkdocs"
Requires-Dist: mkdocstrings[python]>=0.18; extra == "mkdocs"
Requires-Dist: griffe==0.49.0; extra == "mkdocs"
Requires-Dist: griffe-inherited-docstrings; extra == "mkdocs"
Provides-Extra: testing
Requires-Dist: pytest; extra == "testing"
Requires-Dist: sparecores-crawler[mkdocs]; extra == "testing"
Provides-Extra: aws
Requires-Dist: boto3; extra == "aws"
Provides-Extra: hcloud
Requires-Dist: hcloud; extra == "hcloud"
Provides-Extra: gcp
Requires-Dist: google-cloud; extra == "gcp"
Requires-Dist: google-cloud-compute; extra == "gcp"
Requires-Dist: google-cloud-billing; extra == "gcp"
Provides-Extra: azure
Requires-Dist: azure-identity; extra == "azure"
Requires-Dist: azure-mgmt-resource; extra == "azure"
Requires-Dist: azure-mgmt-compute; extra == "azure"
Provides-Extra: upcloud
Requires-Dist: upcloud-api; extra == "upcloud"
Provides-Extra: ovh
Requires-Dist: ovh; extra == "ovh"
Provides-Extra: alicloud
Requires-Dist: alibabacloud-ecs20140526; extra == "alicloud"
Requires-Dist: alibabacloud-bssopenapi20171214; extra == "alicloud"
Provides-Extra: vendors
Requires-Dist: sparecores-crawler[aws]; extra == "vendors"
Requires-Dist: sparecores-crawler[hcloud]; extra == "vendors"
Requires-Dist: sparecores-crawler[gcp]; extra == "vendors"
Requires-Dist: sparecores-crawler[azure]; extra == "vendors"
Requires-Dist: sparecores-crawler[upcloud]; extra == "vendors"
Requires-Dist: sparecores-crawler[ovh]; extra == "vendors"
Requires-Dist: sparecores-crawler[alicloud]; extra == "vendors"
Provides-Extra: all
Requires-Dist: sparecores-crawler[testing]; extra == "all"
Requires-Dist: sparecores-crawler[vendors]; extra == "all"
Dynamic: license-file
